LICENSE
MANIFEST.in
README.rst
setup.py
tambo/__init__.py
tambo/dispatcher.py
tambo/parser.py
tambo.egg-info/PKG-INFO
tambo.egg-info/SOURCES.txt
tambo.egg-info/dependency_links.txt
tambo.egg-info/not-zip-safe
tambo.egg-info/top_level.txt
tambo/tests/__init__.py
tambo/tests/test_dispatcher.py
tambo/tests/test_parser.py