Metadata-Version: 1.1
Name: tambo
Version: 0.1.0
Summary: A command line object dispatcher
Home-page: UNKNOWN
Author: Alfredo Deza
Author-email: alfredodeza [at] gmail.com
License: MIT
Keywords: cli,command,command line,dispatcher,subcommands
Platform: UNKNOWN
Classifier: Development Status :: 4 - Beta
Classifier: Intended Audience :: Developers
Classifier: License :: OSI Approved :: MIT License
Classifier: Topic :: Software Development :: Libraries
Classifier: Topic :: Utilities
Classifier: Operating System :: MacOS :: MacOS X
Classifier: Operating System :: Microsoft :: Windows
Classifier: Operating System :: POSIX
Classifier: Programming Language :: Python :: 2.6
Classifier: Programming Language :: Python :: 2.7
Classifier: Programming Language :: Python :: 3.3
Classifier: Programming Language :: Python :: Implementation :: PyPy
